mtoken/__init__.py
mtoken/token.py
mtoken-0.1.0.dist-info/METADATA
mtoken-0.1.0.dist-info/WHEEL
mtoken-0.1.0.dist-info/top_level.txt
mtoken-0.1.0.dist-info/RECORD
